pymecavideo/PKGBUILD
pymecavideo/__init__.py
pymecavideo/build.py
pymecavideo/cadreur.py
pymecavideo/choix_origine.py
pymecavideo/coordWidget.py
pymecavideo/dbg.py
pymecavideo/detect.py
pymecavideo/echelle.py
pymecavideo/etats.py
pymecavideo/etatsCoord.py
pymecavideo/etatsGraph.py
pymecavideo/etatsMain.py
pymecavideo/etatsPointage.py
pymecavideo/etatsTraj.py
pymecavideo/etats_pymecavideo.dot
pymecavideo/etats_pymecavideo.html
pymecavideo/etats_pymecavideo.md
pymecavideo/etats_pymecavideo.svg
pymecavideo/export.py
pymecavideo/globdef.py
pymecavideo/grandeurs.py
pymecavideo/graphWidget.py
pymecavideo/image_widget.py
pymecavideo/make_exe.py
pymecavideo/nettoyage_exe_windows.py
pymecavideo/pointage.py
pymecavideo/pointageWidget.py
pymecavideo/preferences.py
pymecavideo/pymecavideo.png
pymecavideo/pymecavideo.py
pymecavideo/setup_win.py
pymecavideo/suivi_auto.py
pymecavideo/template_ipynb.py
pymecavideo/testfilm.py
pymecavideo/toQimage.py
pymecavideo/trajWidget.py
pymecavideo/trajectoireWidget.py
pymecavideo/vecteur.py
pymecavideo/version.py
pymecavideo/videoWidget.py
pymecavideo/data/help/curseur_cible-w32.png
pymecavideo/data/help/curseur_cible.svg
pymecavideo/data/help/help-fr.html
pymecavideo/data/help/help-fr.md
pymecavideo/data/help/help-style.css
pymecavideo/data/help/help.css
pymecavideo/data/help/snap1.png
pymecavideo/data/help/snap1.xcf
pymecavideo/data/help/snap10.png
pymecavideo/data/help/snap10.xcf
pymecavideo/data/help/snap11.png
pymecavideo/data/help/snap11.xcf
pymecavideo/data/help/snap12.png
pymecavideo/data/help/snap12.xcf
pymecavideo/data/help/snap13.png
pymecavideo/data/help/snap13.xcf
pymecavideo/data/help/snap14.png
pymecavideo/data/help/snap15.png
pymecavideo/data/help/snap15.xcf
pymecavideo/data/help/snap16.png
pymecavideo/data/help/snap16.xcf
pymecavideo/data/help/snap17.png
pymecavideo/data/help/snap17.xcf
pymecavideo/data/help/snap18.png
pymecavideo/data/help/snap18.xcf
pymecavideo/data/help/snap2-mini.png
pymecavideo/data/help/snap2.png
pymecavideo-8.0rc11.dist-info/METADATA
pymecavideo-8.0rc11.dist-info/WHEEL
pymecavideo-8.0rc11.dist-info/licenses/AUTHORS
pymecavideo-8.0rc11.dist-info/licenses/COPYING
pymecavideo-8.0rc11.dist-info/RECORD
