Metadata-Version: 2.1
Name: pymecavideo
Version: 8.0rc11
Summary: pedagogic tool to analyze video records for mechanics
Project-URL: Homepage, https://outilsphysiques.tuxfamily.org/wiki/index.php?title=Pymecavideo
Project-URL: Bug Tracker, https://gitlab.com/oppl/pymecavideo/-/issues
Author-email: Jean-Baptiste Butet <ashashiwa@gmail.com>, Georges Khaznadar <georgesk@debian.org>, Jd Bourlier <jd.bourlier@gmail.com>, Laurent Godard <lgodard@indesko.com>
License-File: AUTHORS
License-File: COPYING
Classifier: License :: OSI Approved :: GNU General Public License v3 or later (GPLv3+)
Classifier: Operating System :: OS Independent
Classifier: Programming Language :: Python :: 3
Requires-Python: >=3.7
Requires-Dist: opencv-python>=4.7.0.72
Requires-Dist: pyqt6>=6.5.1
Requires-Dist: pyqtgraph>=0.13.3
